redgifs/__init__.py
redgifs/__main__.py
redgifs/aio.py
redgifs/api.py
redgifs/const.py
redgifs/enums.py
redgifs/errors.py
redgifs/http.py
redgifs/models.py
redgifs/parser.py
redgifs/tags.json
redgifs/tags.py
redgifs/utils.py
redgifs/types/gif.py
redgifs/types/image.py
redgifs/types/niches.py
redgifs/types/tags.py
redgifs/types/user.py
redgifs-2.2.0.dist-info/LICENSE
redgifs-2.2.0.dist-info/METADATA
redgifs-2.2.0.dist-info/WHEEL
redgifs-2.2.0.dist-info/entry_points.txt
redgifs-2.2.0.dist-info/top_level.txt
redgifs-2.2.0.dist-info/RECORD
