Metadata-Version: 2.1
Name: redgifs
Version: 2.2.0
Summary: Async and Sync Python Wrapper for the RedGIFs API.
Author: scrazzz
License: The MIT License (MIT)
Project-URL: Documentation, https://redgifs.rtfd.io/en/stable/
Project-URL: Repository, https://github.com/scrazzz/redgifs
Project-URL: Issues, https://github.com/scrazzz/redgifs/issues
Project-URL: Changelogs, https://redgifs.rtfd.io/en/stable/changelogs.html
Keywords: redgifs,api,python,cli,async,sync,aiohttp,requests
Classifier: Development Status :: 5 - Production/Stable
Classifier: License :: OSI Approved :: MIT License
Classifier: Intended Audience :: Science/Research
Classifier: Natural Language :: English
Classifier: Programming Language :: Python :: 3.8
Classifier: Programming Language :: Python :: 3.9
Classifier: Programming Language :: Python :: 3.10
Classifier: Programming Language :: Python :: 3.11
Classifier: Programming Language :: Python :: 3.12
Classifier: Programming Language :: Python :: 3.13
Requires-Python: >=3.8
License-File: LICENSE
Requires-Dist: requests>=2.31.0
Requires-Dist: aiohttp<4,>=3.9.0
Requires-Dist: click>=8
Provides-Extra: docs
Requires-Dist: Sphinx==6.0; extra == "docs"
Requires-Dist: furo==2024.01.29; extra == "docs"
Provides-Extra: test
Requires-Dist: pytest==8.3.5; extra == "test"
